README.md
setup.py
linkedin_user_scrape/__init__.py
linkedin_user_scrape/scraper.py
linkedin_user_scrape/utils.py
linkedin_user_scrape.egg-info/PKG-INFO
linkedin_user_scrape.egg-info/SOURCES.txt
linkedin_user_scrape.egg-info/dependency_links.txt
linkedin_user_scrape.egg-info/requires.txt
linkedin_user_scrape.egg-info/top_level.txt